[
  {
    "id": "PRJ-1001",
    "name": "Two-storey extension — Prince Edward Dr",
    "client": "Harrington Homes",
    "address": "47 Prince Edward Dr",
    "suburb": "Dapto",
    "state": "NSW",
    "postcode": "2530",
    "lat": -34.4989,
    "lng": 150.7907,
    "price": 15700,
    "status": "live",
    "createdAt": "2026-06-02T00:00:00.000Z"
  },
  {
    "id": "PRJ-1002",
    "name": "Reroof + gutter line — Lawrence Hargrave Dr",
    "client": "Coastline Roofing",
    "address": "23 Lawrence Hargrave Dr",
    "suburb": "Thirroul",
    "state": "NSW",
    "postcode": "2515",
    "lat": -34.3157,
    "lng": 150.921,
    "price": 6800,
    "status": "order",
    "createdAt": "2026-06-18T00:00:00.000Z"
  },
  {
    "id": "PRJ-1003",
    "name": "Duplex render — Addison Ave",
    "client": "Brickfield Constructions",
    "address": "8 Addison Ave",
    "suburb": "Shellharbour",
    "state": "NSW",
    "postcode": "2529",
    "lat": -34.5794,
    "lng": 150.8664,
    "price": 12500,
    "status": "booked",
    "createdAt": "2026-06-25T00:00:00.000Z"
  },
  {
    "id": "PRJ-1004",
    "name": "Heritage repaint — Manning St",
    "client": "Kiama Council",
    "address": "30 Manning St",
    "suburb": "Kiama",
    "state": "NSW",
    "postcode": "2533",
    "lat": -34.6713,
    "lng": 150.8542,
    "price": 9200,
    "status": "off-hired",
    "createdAt": "2026-05-11T00:00:00.000Z"
  },
  {
    "id": "PRJ-1005",
    "name": "New build — Robsons Rd",
    "client": "Marrick Building Co",
    "address": "14 Robsons Rd",
    "suburb": "Keiraville",
    "state": "NSW",
    "postcode": "2500",
    "lat": -34.4136,
    "lng": 150.8723,
    "price": 18400,
    "status": "live",
    "createdAt": "2026-06-09T00:00:00.000Z"
  },
  {
    "id": "PRJ-1006",
    "name": "Fascia + solar edge protection — Railway St",
    "client": "Illawarra Solar Group",
    "address": "12 Railway St",
    "suburb": "Corrimal",
    "state": "NSW",
    "postcode": "2518",
    "lat": -34.3784,
    "lng": 150.8951,
    "price": 4300,
    "status": "enquiry",
    "createdAt": "2026-07-08T00:00:00.000Z"
  }
]
